dftbook/__init__.py
dftbook/setup.py
dftbook-0.0.5.dist-info/METADATA
dftbook-0.0.5.dist-info/WHEEL
dftbook-0.0.5.dist-info/top_level.txt
dftbook-0.0.5.dist-info/RECORD
