Metadata-Version: 2.1
Name: dftbook
Version: 0.0.5
Summary: Module for setting up dft-book tutorials
Home-page: http://github.com/jkitchin/dftbook
Author: John Kitchin, Zack Ulissi
Author-email: jkitchin@andrew.cmu.edu
License: GPL
Platform: UNKNOWN
